wfrappi/__init__.py
wfrappi/data_processing.py
wfrappi/dbconn.py
wfrappi/fetch_data.py
wfrappi/main.py
wfrappi/modeling.py
wfrappi/order_distribution.py
wfm_rappi_co-0.1.0.dist-info/METADATA
wfm_rappi_co-0.1.0.dist-info/WHEEL
wfm_rappi_co-0.1.0.dist-info/top_level.txt
wfm_rappi_co-0.1.0.dist-info/RECORD
