Metadata-Version: 2.1
Name: wfm_rappi_co
Version: 0.1.0
Requires-Dist: pandas ==2.1.4
Requires-Dist: numpy ==1.26.4
Requires-Dist: scikit-learn ==1.3.2
Requires-Dist: xgboost ==2.0.3
Requires-Dist: snowflake-connector-python ==3.7.1
Requires-Dist: snowflake-snowpark-python ==1.13.0
Requires-Dist: pyarrow ==16.1.0
